lotame/__init__.py
lotame/lotame.py
tests/__init__.py
tests/test_lotame.py
lotame-2.0.0.dist-info/LICENSE
lotame-2.0.0.dist-info/METADATA
lotame-2.0.0.dist-info/WHEEL
lotame-2.0.0.dist-info/top_level.txt
lotame-2.0.0.dist-info/RECORD
