Metadata-Version: 2.1
Name: lotame
Version: 2.0.0
Summary: Simple python wrapper for LOTAME API
Home-page: https://github.com/paulokuong/lotame
Author: Paulo Kuong
Author-email: paulo.kuong@gmail.com
License: MIT
Keywords: lotame python wrapper client audience behavior api sdk
Platform: UNKNOWN
Classifier: Development Status :: 3 - Alpha
Classifier: License :: OSI Approved :: MIT License
Classifier: Programming Language :: Python :: 3.6
Requires-Dist: httplib2 (==0.10.3)
Requires-Dist: urllib3 (>=1.23)
Requires-Dist: requests (==2.21.0)
